CHANGELOG.md
LICENSE
README.md
ST7789.py
st7789/__init__.py
st7789-1.0.0.dist-info/METADATA
st7789-1.0.0.dist-info/WHEEL
st7789-1.0.0.dist-info/licenses/LICENSE
st7789-1.0.0.dist-info/RECORD
