Metadata-Version: 2.3
Name: st7789
Version: 1.0.0
Summary: Driver for ST7789-based TFT LCD displays.
Project-URL: GitHub, https://www.github.com/pimoroni/st7789-python
Project-URL: Homepage, https://www.pimoroni.com
Author-email: Philip Howard <phil@pimoroni.com>
Maintainer-email: Philip Howard <phil@pimoroni.com>
License: The MIT License (MIT)
License-File: LICENSE
Keywords: Pi,Raspberry
Classifier: Development Status :: 4 - Beta
Classifier: Intended Audience :: Developers
Classifier: License :: OSI Approved :: MIT License
Classifier: Operating System :: POSIX :: Linux
Classifier: Programming Language :: Python :: 3
Classifier: Programming Language :: Python :: 3 :: Only
Classifier: Programming Language :: Python :: 3.7
Classifier: Programming Language :: Python :: 3.8
Classifier: Programming Language :: Python :: 3.9
Classifier: Programming Language :: Python :: 3.10
Classifier: Programming Language :: Python :: 3.11
Classifier: Topic :: Software Development
Classifier: Topic :: Software Development :: Libraries
Classifier: Topic :: System :: Hardware
Requires-Python: >=3.7
Requires-Dist: gpiod
Requires-Dist: gpiodevice>=0.0.4
